ai_posture_monitor/__init__.py
ai_posture_monitor/evaluation_dependencies.py
ai_posture_monitor/features_dependencies.py
ai_posture_monitor/frame_diff_dependencies.py
ai_posture_monitor/plot_dependencies.py
ai_posture_monitor/pose_est_dependencies.py
ai_posture_monitor/predict_dependencies.py
ai_posture_monitor-0.0.14.dist-info/LICENSE
ai_posture_monitor-0.0.14.dist-info/METADATA
ai_posture_monitor-0.0.14.dist-info/WHEEL
ai_posture_monitor-0.0.14.dist-info/top_level.txt
ai_posture_monitor-0.0.14.dist-info/RECORD
