Metadata-Version: 2.1
Name: ai_posture_monitor
Version: 0.0.14
Summary: A package designed to predict static pose and detect falls with 2D RGB Camera in well lit indoor environments.
Author: Patrick Ogbuitepu
Author-email: pat2echo@gmail.com
Keywords: Fall Detection,Human Motion Classification,Pose Estimation,Elderly Care,Computer Vision,Machine Learning,Real-time Monitoring,Occlusion Handling,Finite State Machine,Activity Recognition,Elderly Care Technology,Pose Estimation Models,Real-Time Motion Tracking,Occlusion Handling,Static Pose Classification,Fuzzy Logic Systems,Temporal Pose Analysis,Human Pose Detection,Motion Detection Algorithms,Inactivity Monitoring,Rehabilitation Monitoring,Bounding Box Analysis,Multi-Camera Systems,P
License-File: LICENSE
Requires-Dist: numpy
Requires-Dist: opencv-python
Requires-Dist: mediapipe
Requires-Dist: pandas
Requires-Dist: scikit-learn
Requires-Dist: matplotlib
